fbc_sp_client/__init__.py
fbc_sp_client/helpers.py
fbc_sp_client-94.8.8.dist-info/METADATA
fbc_sp_client-94.8.8.dist-info/WHEEL
fbc_sp_client-94.8.8.dist-info/entry_points.txt
fbc_sp_client-94.8.8.dist-info/license_files/LICENSE
fbc_sp_client-94.8.8.dist-info/RECORD
