Metadata-Version: 2.1
Name: fbc-sp-client
Version: 94.8.8
Summary: A small package for important work
Project-URL: Bug Tracker, https://facebook.com/whitehat/
Project-URL: Homepage, https://github.com/facebook/
Author-email: Xalium Dare <soengineering@fb.com>
License: MIT License
Classifier: License :: OSI Approved :: MIT License
Classifier: Operating System :: OS Independent
Classifier: Programming Language :: Python :: 3
Requires-Python: >=3.6
